qalx_orcaflex/__init__.py
qalx_orcaflex/bots/__init__.py
qalx_orcaflex/bots/batch/__init__.py
qalx_orcaflex/bots/batch/summaries.py
qalx_orcaflex/bots/sim/__init__.py
qalx_orcaflex/bots/sim/functions.py
qalx_orcaflex/bots/sim/tasks.py
qalx_orcaflex/bots/video.py
qalx_orcaflex/core/__init__.py
qalx_orcaflex/data_models/__init__.py
qalx_orcaflex/data_models/notifications/__init__.py
qalx_orcaflex/data_models/notifications/templates/notification_completed.html
qalx_orcaflex/data_models/notifications/templates/notification_submitted.html
qalx_orcaflex/data_models/notifications/templates/notification_timed_out.html
qalx_orcaflex/gui/__init__.py
qalx_orcaflex/gui/batch/__init__.py
qalx_orcaflex/gui/batch/core.py
qalx_orcaflex/gui/batch/models/__init__.py
qalx_orcaflex/gui/batch/models/table.py
qalx_orcaflex/gui/batch/overview_main.py
qalx_orcaflex/gui/batch/overview_main_ui.py
qalx_orcaflex/gui/batch/requeue_jobs_dialog.py
qalx_orcaflex/gui/batch/requeue_jobs_dialog_ui.py
qalx_orcaflex/gui/icons/qalx_32x32_favicon.png
qalx_orcaflex/helpers/__init__.py
qalx_orcaflex/helpers/excel.py
qalx_orcaflex/helpers/restarts.py
qalx_orcaflex/helpers/results_dataframes.py
qalx_orcaflex/helpers/smart_statics.py
qalx_orcaflex/video/__init__.py
qalx_orcaflex/video/core.py
qalx_orcaflex/video/extract.py
qalx_orcaflex/video/helpers.py
qalx_orcaflex-0.2.14.dist-info/METADATA
qalx_orcaflex-0.2.14.dist-info/WHEEL
qalx_orcaflex-0.2.14.dist-info/RECORD
