Metadata-Version: 2.1
Name: qalx-orcaflex
Version: 0.2.14
Summary: qalx bots and helpers for OrcaFlex
License: GPL-3.0+
Author: Steven Rossiter
Author-email: steve@agiletek.co.uk
Requires-Python: >=3.8.0,<4.0.0
Classifier: License :: OSI Approved :: GNU General Public License v3 or later (GPLv3+)
Classifier: Programming Language :: Python :: 3
Classifier: Programming Language :: Python :: 3.8
Classifier: Programming Language :: Python :: 3.9
Classifier: Programming Language :: Python :: 3.10
Classifier: Programming Language :: Python :: 3.11
Classifier: Programming Language :: Python :: 3.12
Provides-Extra: docs
Provides-Extra: flaky
Provides-Extra: pip-licenses
Requires-Dist: OrcFxAPI (>=11.0.2,<12.0.0)
Requires-Dist: flaky (>=3.8.1,<4.0.0) ; extra == "flaky"
Requires-Dist: pandas (>=1.0.4,<2.0.0)
Requires-Dist: pip-licenses (>=4.3,<5.0) ; extra == "pip-licenses"
Requires-Dist: psutil (>=5.7.0,<6.0.0)
Requires-Dist: pyqalx (>=0.19.2,<0.20.0)
Requires-Dist: pyqt5 (==5.15.2) ; platform_machine != "arm64"
Requires-Dist: pyqt5 (>=5.15.2,<6.0.0) ; platform_machine == "arm64"
Requires-Dist: pyyaml (>=5.3.1,<6.0.0)
Requires-Dist: sphinx (<7.2) ; extra == "docs"
Requires-Dist: sphinx-rtd-theme (>=2.0.0,<3.0.0) ; extra == "docs"
Requires-Dist: toml (>=0.10.2,<0.11.0) ; extra == "docs"
Project-URL: Documentation, https://orcaflex.qalx.net
